tuning_box/__init__.py
tuning_box/app.py
tuning_box/client.py
tuning_box/converters.py
tuning_box/db.py
tuning_box/fuelclient.py
tuning_box/nailgun.py
tuning_box/cli/__init__.py
tuning_box/cli/base.py
tuning_box/cli/get.py
tuning_box/cli/set.py
tuning_box/migrations/env.py
tuning_box/migrations/script.py.mako
tuning_box/migrations/versions/3b2a0f134e45_switch_to_new_api.py
tuning_box/migrations/versions/967a44dd16d5_add_server_default_to_resource_values_values.py
tuning_box/migrations/versions/9ae15c85fa92_remove_fake_root_hierarchy_level_values.py
tuning_box/migrations/versions/ad192a40fd68_add_overrides_to_resource_values.py
tuning_box/migrations/versions/d054eefc4c5b_add_unique_constraint_on_component_name.py
tuning_box/migrations/versions/f16eb4eff7c_initial_revision.py
tuning_box/tests/__init__.py
tuning_box/tests/base.py
tuning_box/tests/test_app.py
tuning_box/tests/test_cli.py
tuning_box/tests/test_converters.py
tuning_box/tests/test_db.py
tuning_box-0.1.0.dist-info/DESCRIPTION.rst
tuning_box-0.1.0.dist-info/METADATA
tuning_box-0.1.0.dist-info/RECORD
tuning_box-0.1.0.dist-info/WHEEL
tuning_box-0.1.0.dist-info/entry_points.txt
tuning_box-0.1.0.dist-info/metadata.json
tuning_box-0.1.0.dist-info/pbr.json
tuning_box-0.1.0.dist-info/top_level.txt
