Metadata-Version: 2.0
Name: tuning-box
Version: 0.1.0
Summary: Tuning Box - configuration storage for your clouds
Home-page: http://www.openstack.org/
Author: OpenStack
Author-email: openstack-dev@lists.openstack.org
License: UNKNOWN
Platform: UNKNOWN
Classifier: Environment :: OpenStack
Classifier: Intended Audience :: Information Technology
Classifier: Intended Audience :: System Administrators
Classifier: License :: OSI Approved :: Apache Software License
Classifier: Operating System :: POSIX :: Linux
Classifier: Programming Language :: Python
Classifier: Programming Language :: Python :: 2
Classifier: Programming Language :: Python :: 2.7
Classifier: Programming Language :: Python :: 3
Classifier: Programming Language :: Python :: 3.3
Classifier: Programming Language :: Python :: 3.4
Requires-Dist: alembic
Requires-Dist: cliff
Requires-Dist: flask
Requires-Dist: flask-restful
Requires-Dist: flask-sqlalchemy
Requires-Dist: pbr (>=1.6)
Requires-Dist: requests
